{
  "latest-preset": {
    "theme": "dracula-pro",
    "backgroundColor": "white",
    "windowTheme": "none",
    "windowControls": true,
    "fontFamily": "Space Mono",
    "fontSize": "108px",
    "lineNumbers": false,
    "firstLineNumber": 1,
    "selectedLines": "*",
    "dropShadow": false,
    "dropShadowOffsetY": "20px",
    "dropShadowBlurRadius": "68px",
    "widthAdjustment": true,
    "lineHeight": "140%",
    "paddingVertical": "35px",
    "paddingHorizontal": "35px",
    "squaredImage": false,
    "watermark": false,
    "exportSize": "2x",
    "type": "png"
  },
  "presentation": {
    "theme": "base16-dark",
    "backgroundColor": "transparent",
    "windowTheme": "none",
    "windowControls": false,
    "fontFamily": "Source Code Pro",
    "fontSize": "21px",
    "lineNumbers": false,
    "firstLineNumber": 1,
    "selectedLines": "*",
    "dropShadow": true,
    "dropShadowOffsetY": "2px",
    "dropShadowBlurRadius": "5px",
    "widthAdjustment": true,
    "lineHeight": "133%",
    "paddingVertical": "0",
    "paddingHorizontal": "0",
    "squaredImage": false,
    "watermark": false,
    "exportSize": "4x",
    "type": "png"
  }
}